roseau/load_flow_single/__about__.py
roseau/load_flow_single/__init__.py
roseau/load_flow_single/_constants.py
roseau/load_flow_single/network.py
roseau/load_flow_single/io/__init__.py
roseau/load_flow_single/io/dict.py
roseau/load_flow_single/models/__init__.py
roseau/load_flow_single/models/branches.py
roseau/load_flow_single/models/buses.py
roseau/load_flow_single/models/core.py
roseau/load_flow_single/models/flexible_parameters.py
roseau/load_flow_single/models/line_parameters.py
roseau/load_flow_single/models/lines.py
roseau/load_flow_single/models/loads.py
roseau/load_flow_single/models/sources.py
roseau/load_flow_single/models/switches.py
roseau/load_flow_single/models/transformers.py
roseau_load_flow_single-0.1.0.dist-info/METADATA
roseau_load_flow_single-0.1.0.dist-info/WHEEL
roseau_load_flow_single-0.1.0.dist-info/licenses/LICENSE.md
roseau_load_flow_single-0.1.0.dist-info/RECORD
