Metadata-Version: 2.3
Name: roseau-load-flow-single
Version: 0.1.0
Summary: Highly capable single-phase load flow solver
Project-URL: repository, https://github.com/RoseauTechnologies/Roseau_Load_Flow_Single/
Project-URL: issues, https://github.com/RoseauTechnologies/Roseau_Load_Flow_Single/issues/
Project-URL: documentation, https://roseau-load-flow.roseautechnologies.com/
Author-email: Ali Hamdan <ali.hamdan@roseautechnologies.com>, Sébastien Vallet <sebastien.vallet@roseautechnologies.com>, Benoît Vinot <benoit.vinot@roseautechnologies.com>, Florent Cadoux <florent.cadoux@roseautechnologies.com>
Maintainer-email: Ali Hamdan <ali.hamdan@roseautechnologies.com>
License: BSD 3-Clause License
Classifier: Development Status :: 3 - Alpha
Classifier: Operating System :: MacOS :: MacOS X
Classifier: Operating System :: Microsoft :: Windows
Classifier: Operating System :: POSIX :: Linux
Classifier: Programming Language :: Python :: 3.10
Classifier: Programming Language :: Python :: 3.11
Classifier: Programming Language :: Python :: 3.12
Classifier: Programming Language :: Python :: 3.13
Classifier: Topic :: Scientific/Engineering :: Physics
Requires-Python: >=3.10
Requires-Dist: certifi>=2023.5.7
Requires-Dist: geopandas>=1.0.0
Requires-Dist: numpy>=1.21.5
Requires-Dist: pandas>=1.4.0
Requires-Dist: pint>=0.21.0
Requires-Dist: platformdirs>=4.0.0
Requires-Dist: pyproj>=3.3.0
Requires-Dist: roseau-load-flow-engine==0.16.0
Requires-Dist: roseau-load-flow==0.11.0
Requires-Dist: shapely>=2.0.0
Requires-Dist: typing-extensions>=4.6.2
Provides-Extra: graph
Requires-Dist: networkx>=3.0.0; extra == 'graph'
Provides-Extra: plot
Requires-Dist: matplotlib>=3.7.2; extra == 'plot'
